{"cameraMode":{"drawMode":0,"name":"Shaded","section":"Shading Mode"},"sceneLighting":true,"audioPlay":false,"sceneViewState":{"m_AlwaysRefresh":false,"showFog":true,"showSkybox":true,"showFlares":true,"showImageEffects":true,"showParticleSystems":true,"showVisualEffectGraphs":true,"m_FxEnabled":true},"in2DMode":false,"pivot":{"x":19.058879852294923,"y":11.047106742858887,"z":-15.239927291870118},"rotation":{"x":-0.13773676753044129,"y":-0.6863120794296265,"z":0.13460849225521089,"w":-0.701278805732727},"size":13.86188793182373,"orthographic":false}